django_simple_ratings-0.3.3.dist-info/DESCRIPTION.rst
django_simple_ratings-0.3.3.dist-info/METADATA
django_simple_ratings-0.3.3.dist-info/pydist.json
django_simple_ratings-0.3.3.dist-info/RECORD
django_simple_ratings-0.3.3.dist-info/top_level.txt
django_simple_ratings-0.3.3.dist-info/WHEEL
ratings/__init__.py
ratings/models.py
ratings/urls.py
ratings/utils.py
ratings/views.py
ratings/management/__init__.py
ratings/management/commands/__init__.py
ratings/management/commands/update_similar_items.py
ratings/migrations/0001_initial.py
ratings/migrations/__init__.py
ratings/ratings_tests/__init__.py
ratings/ratings_tests/models.py
ratings/ratings_tests/tests.py
ratings/ratings_tests/urls.py
ratings/templatetags/__init__.py
ratings/templatetags/ratings_tags.py
