Metadata-Version: 1.1
Name: django-simple-ratings
Version: 0.3.3
Summary: a simple, extensible rating system.
Home-page: http://github.com/django-de/django-simple-ratings/tree/master
Author: Deutscher Django Verein e. V.
Author-email: kontakt@django-de.org
License: UNKNOWN
Platform: UNKNOWN
Classifier: Development Status :: 4 - Beta
Classifier: Environment :: Web Environment
Classifier: Intended Audience :: Developers
Classifier: License :: OSI Approved :: MIT License
Classifier: Operating System :: OS Independent
Classifier: Programming Language :: Python
Classifier: Framework :: Django
